README.md
setup.py
cansi/__init__.py
cansi/ansi.py
cansi/cansi.py
cansi/color.py
cansi.egg-info/PKG-INFO
cansi.egg-info/SOURCES.txt
cansi.egg-info/dependency_links.txt
cansi.egg-info/top_level.txt